lcEnhance/LCE.py
lcEnhance/__init__.py
lcenhance-1.0.0.dist-info/licenses/LICENSE
lcenhance-1.0.0.dist-info/METADATA
lcenhance-1.0.0.dist-info/WHEEL
lcenhance-1.0.0.dist-info/top_level.txt
lcenhance-1.0.0.dist-info/RECORD
