Metadata-Version: 2.4
Name: lcEnhance
Version: 1.0.0
License-File: LICENSE
Requires-Dist: numpy
Requires-Dist: astropy
Requires-Dist: matplotlib
Dynamic: license-file
